rpi_courses
test
