Metadata-Version: 1.1
Name: RPICourses
Version: 1.0.9
Summary: A data scraping library to read course data from RPI.
Home-page: https://github.com/jeffh/rpi_courses
Author: Jeff Hui
Author-email: jeff@jeffhui.net
License: MIT
Platform: UNKNOWN
Classifier: Development Status :: 5 - Production/Stable
Classifier: Intended Audience :: Developers
Classifier: Programming Language :: Python :: 2.6
Classifier: Operating System :: OS Independent
Classifier: License :: OSI Approved :: MIT License
Classifier: Topic :: Software Development :: Libraries
Requires: BeautifulSoup
Requires: PyPDF2
Requires: pyconstraints
